modern_logger/__init__.py
modern_logger/gui_adapter.py
modern_logger/gui_logger.py
modern_logger/logger.py
modern_logger-1.0.0.dist-info/licenses/LICENSE
modern_logger-1.0.0.dist-info/METADATA
modern_logger-1.0.0.dist-info/WHEEL
modern_logger-1.0.0.dist-info/top_level.txt
modern_logger-1.0.0.dist-info/RECORD
