Metadata-Version: 2.4
Name: modern-logger
Version: 1.0.0
Summary: A flexible logging system with file, console, and GUI (PySide6) output options
Home-page: https://github.com/Mola-TT/Modern-Logger
Author: Mola
Author-email: Mola <mola@molamola.me>
License: MIT
Project-URL: Homepage, https://github.com/Mola-TT/Modern-Logger
Project-URL: Repository, https://github.com/Mola-TT/Modern-Logger
Project-URL: Issues, https://github.com/Mola-TT/Modern-Logger/issues
Keywords: logging,console,file,gui,qt,pyside6,modern
Classifier: Development Status :: 5 - Production/Stable
Classifier: Intended Audience :: Developers
Classifier: License :: OSI Approved :: MIT License
Classifier: Programming Language :: Python :: 3
Classifier: Programming Language :: Python :: 3.7
Classifier: Programming Language :: Python :: 3.8
Classifier: Programming Language :: Python :: 3.9
Classifier: Programming Language :: Python :: 3.10
Classifier: Programming Language :: Python :: 3.11
Classifier: Programming Language :: Python :: 3.12
Requires-Python: >=3.7
License-File: LICENSE
Requires-Dist: colorama>=0.4.4
Provides-Extra: gui
Requires-Dist: PySide6>=6.0.0; extra == "gui"
Provides-Extra: dev
Requires-Dist: PySide6>=6.0.0; extra == "dev"
Dynamic: author
Dynamic: home-page
Dynamic: license-file
Dynamic: requires-python
